llama_index/indices/managed/vertexai/__init__.py
llama_index/indices/managed/vertexai/base.py
llama_index/indices/managed/vertexai/retriever.py
llama_index_indices_managed_vertexai-0.3.1.dist-info/METADATA
llama_index_indices_managed_vertexai-0.3.1.dist-info/WHEEL
llama_index_indices_managed_vertexai-0.3.1.dist-info/licenses/LICENSE
llama_index_indices_managed_vertexai-0.3.1.dist-info/RECORD
