Metadata-Version: 2.4
Name: llama-index-indices-managed-vertexai
Version: 0.3.1
Summary: llama-index managed Vertex AI integration
Author-email: Holt Skinner <holtskinner@google.com>
License-Expression: MIT
License-File: LICENSE
Requires-Python: <4.0,>=3.9
Requires-Dist: google-cloud-aiplatform>=1.53.0
Requires-Dist: llama-index-core<0.15,>=0.13.0
